pycryptaes/__init__.py
pycryptaes/main.py
pycryptaes-0.1.4.dist-info/WHEEL
pycryptaes-0.1.4.dist-info/METADATA
pycryptaes-0.1.4.dist-info/RECORD
